CHANGES.rst
LICENSE.txt
MANIFEST.in
README.rst
TODO.txt
VERSION.txt
setup.py
bin/make.py
bin/work
bin/workadd
bin/workcd
bin/workmake
bin/workon
litework/__init__.py
litework.egg-info/PKG-INFO
litework.egg-info/SOURCES.txt
litework.egg-info/dependency_links.txt
litework.egg-info/top_level.txt