Metadata-Version: 1.0
Name: litework
Version: 0.1.0
Summary: Tools for rapidly preparing PyPI projects
Home-page: http://pypi.python.org/pypi/litework/
Author: Matthew Cotton
Author-email: matt@thecottons.com
License: MIT - LICENSE.txt
Platform: UNKNOWN
